{
  "updated": "2026-06-29",
  "source": "best-effort multi-site scrape \u2014 30/30 cities refreshed 2026-06-29",
  "cities": [
    {
      "city": "Delhi",
      "state": "Delhi",
      "petrol": 102.12,
      "diesel": 95.2
    },
    {
      "city": "Mumbai",
      "state": "Maharashtra",
      "petrol": 111.21,
      "diesel": 97.83
    },
    {
      "city": "Chennai",
      "state": "Tamil Nadu",
      "petrol": 107.76,
      "diesel": 99.55
    },
    {
      "city": "Kolkata",
      "state": "West Bengal",
      "petrol": 113.47,
      "diesel": 99.82
    },
    {
      "city": "Bengaluru",
      "state": "Karnataka",
      "petrol": 111.68,
      "diesel": 99.56
    },
    {
      "city": "Hyderabad",
      "state": "Telangana",
      "petrol": 115.69,
      "diesel": 103.82
    },
    {
      "city": "Pune",
      "state": "Maharashtra",
      "petrol": 111.65,
      "diesel": 98.3
    },
    {
      "city": "Ahmedabad",
      "state": "Gujarat",
      "petrol": 101.81,
      "diesel": 97.92
    },
    {
      "city": "Jaipur",
      "state": "Rajasthan",
      "petrol": 113.35,
      "diesel": 98.39
    },
    {
      "city": "Lucknow",
      "state": "Uttar Pradesh",
      "petrol": 102.08,
      "diesel": 95.56
    },
    {
      "city": "Noida",
      "state": "Uttar Pradesh",
      "petrol": 102.08,
      "diesel": 95.56
    },
    {
      "city": "Chandigarh",
      "state": "Chandigarh",
      "petrol": 101.54,
      "diesel": 89.47
    },
    {
      "city": "Bhopal",
      "state": "Madhya Pradesh",
      "petrol": 114.65,
      "diesel": 99.74
    },
    {
      "city": "Indore",
      "state": "Madhya Pradesh",
      "petrol": 114.58,
      "diesel": 99.7
    },
    {
      "city": "Patna",
      "state": "Bihar",
      "petrol": 113.37,
      "diesel": 99.36
    },
    {
      "city": "Ranchi",
      "state": "Jharkhand",
      "petrol": 105.26,
      "diesel": 100.49
    },
    {
      "city": "Raipur",
      "state": "Chhattisgarh",
      "petrol": 108.06,
      "diesel": 101.32
    },
    {
      "city": "Bhubaneswar",
      "state": "Odisha",
      "petrol": 108.97,
      "diesel": 100.68
    },
    {
      "city": "Guwahati",
      "state": "Assam",
      "petrol": 105.74,
      "diesel": 97.23
    },
    {
      "city": "Thiruvananthapuram",
      "state": "Kerala",
      "petrol": 115.49,
      "diesel": 104.4
    },
    {
      "city": "Kochi",
      "state": "Kerala",
      "petrol": 115.34,
      "diesel": 104.15
    },
    {
      "city": "Coimbatore",
      "state": "Tamil Nadu",
      "petrol": 107.76,
      "diesel": 99.55
    },
    {
      "city": "Visakhapatnam",
      "state": "Andhra Pradesh",
      "petrol": 116.39,
      "diesel": 104.11
    },
    {
      "city": "Nagpur",
      "state": "Maharashtra",
      "petrol": 111.72,
      "diesel": 98.38
    },
    {
      "city": "Surat",
      "state": "Gujarat",
      "petrol": 101.81,
      "diesel": 97.92
    },
    {
      "city": "Vadodara",
      "state": "Gujarat",
      "petrol": 101.81,
      "diesel": 97.92
    },
    {
      "city": "Ludhiana",
      "state": "Punjab",
      "petrol": 105.12,
      "diesel": 95.05
    },
    {
      "city": "Agra",
      "state": "Uttar Pradesh",
      "petrol": 102.08,
      "diesel": 95.56
    },
    {
      "city": "Varanasi",
      "state": "Uttar Pradesh",
      "petrol": 102.08,
      "diesel": 95.56
    },
    {
      "city": "Dehradun",
      "state": "Uttarakhand",
      "petrol": 100.54,
      "diesel": 95.05
    }
  ],
  "prices_verified": "2026-06-29"
}